services/__init__.py
services/admin.py
services/apps.py
services/static/css/services/bethany_ds.css
services/static/css/services/medicio_ds.css
services/static/css/services/medilab_ds.css
services/templates/services/_common.html
services/templates/services/bethany_ds.html
services/templates/services/medicio_ds.html
services/templates/services/medilab_ds.html
services/templatetags/__init__.py
services/templatetags/services_tags.py
django_services_ds-0.1.1.dist-info/LICENSE
django_services_ds-0.1.1.dist-info/METADATA
django_services_ds-0.1.1.dist-info/WHEEL
django_services_ds-0.1.1.dist-info/top_level.txt
django_services_ds-0.1.1.dist-info/RECORD
